tinygrad/__init__.py
tinygrad/device.py
tinygrad/dtype.py
tinygrad/function.py
tinygrad/helpers.py
tinygrad/lazy.py
tinygrad/multi.py
tinygrad/ops.py
tinygrad/tensor.py
tinygrad/codegen/__init__.py
tinygrad/codegen/kernel.py
tinygrad/codegen/lowerer.py
tinygrad/codegen/transcendental.py
tinygrad/codegen/uopgraph.py
tinygrad/codegen/uops.py
tinygrad/engine/__init__.py
tinygrad/engine/graph.py
tinygrad/engine/jit.py
tinygrad/engine/realize.py
tinygrad/engine/schedule.py
tinygrad/engine/search.py
tinygrad/nn/__init__.py
tinygrad/nn/datasets.py
tinygrad/nn/optim.py
tinygrad/nn/state.py
tinygrad/renderer/__init__.py
tinygrad/renderer/assembly.py
tinygrad/renderer/cstyle.py
tinygrad/renderer/llvmir.py
tinygrad/runtime/__init__.py
tinygrad/runtime/ops_amd.py
tinygrad/runtime/ops_clang.py
tinygrad/runtime/ops_cuda.py
tinygrad/runtime/ops_disk.py
tinygrad/runtime/ops_gpu.py
tinygrad/runtime/ops_hip.py
tinygrad/runtime/ops_llvm.py
tinygrad/runtime/ops_metal.py
tinygrad/runtime/ops_npy.py
tinygrad/runtime/ops_nv.py
tinygrad/runtime/ops_python.py
tinygrad/runtime/autogen/amd_gpu.py
tinygrad/runtime/autogen/comgr.py
tinygrad/runtime/autogen/cuda.py
tinygrad/runtime/autogen/hip.py
tinygrad/runtime/autogen/hsa.py
tinygrad/runtime/autogen/io_uring.py
tinygrad/runtime/autogen/kfd.py
tinygrad/runtime/autogen/libc.py
tinygrad/runtime/autogen/nv_gpu.py
tinygrad/runtime/autogen/nvrtc.py
tinygrad/runtime/autogen/opencl.py
tinygrad/runtime/graph/__init__.py
tinygrad/runtime/graph/clang.py
tinygrad/runtime/graph/cuda.py
tinygrad/runtime/graph/hcq.py
tinygrad/runtime/graph/metal.py
tinygrad/runtime/support/__init__.py
tinygrad/runtime/support/compiler_cuda.py
tinygrad/runtime/support/compiler_hip.py
tinygrad/runtime/support/elf.py
tinygrad/shape/__init__.py
tinygrad/shape/shapetracker.py
tinygrad/shape/symbolic.py
tinygrad/shape/view.py
tinygrad_tools-0.10.2.dist-info/LICENSE
tinygrad_tools-0.10.2.dist-info/METADATA
tinygrad_tools-0.10.2.dist-info/WHEEL
tinygrad_tools-0.10.2.dist-info/top_level.txt
tinygrad_tools-0.10.2.dist-info/RECORD
