Metadata-Version: 2.1
Name: tinygrad-tools
Version: 0.10.2
Summary: You like pytorch? You like micrograd? You love tinygrad! <3
Author: George Hotz
License: MIT
Classifier: Programming Language :: Python :: 3
Classifier: License :: OSI Approved :: MIT License
Requires-Python: >=3.8
License-File: LICENSE
Requires-Dist: numpy
Requires-Dist: pyobjc-framework-Metal ; platform_system == "Darwin"
Requires-Dist: pyobjc-framework-libdispatch ; platform_system == "Darwin"
Provides-Extra: arm
Requires-Dist: unicorn ; extra == 'arm'
Provides-Extra: docs
Requires-Dist: mkdocs ; extra == 'docs'
Requires-Dist: mkdocs-material ; extra == 'docs'
Requires-Dist: mkdocstrings[python] ; extra == 'docs'
Requires-Dist: markdown-callouts ; extra == 'docs'
Requires-Dist: markdown-exec[ansi] ; extra == 'docs'
Requires-Dist: black ; extra == 'docs'
Provides-Extra: linting
Requires-Dist: pylint ; extra == 'linting'
Requires-Dist: mypy ; extra == 'linting'
Requires-Dist: typing-extensions ; extra == 'linting'
Requires-Dist: pre-commit ; extra == 'linting'
Requires-Dist: ruff ; extra == 'linting'
Requires-Dist: types-tqdm ; extra == 'linting'
Provides-Extra: llvm
Requires-Dist: llvmlite ; extra == 'llvm'
Provides-Extra: testing
Requires-Dist: torch ; extra == 'testing'
Requires-Dist: pillow ; extra == 'testing'
Requires-Dist: pytest ; extra == 'testing'
Requires-Dist: pytest-xdist ; extra == 'testing'
Requires-Dist: onnx ==1.16.0 ; extra == 'testing'
Requires-Dist: onnx2torch ; extra == 'testing'
Requires-Dist: opencv-python ; extra == 'testing'
Requires-Dist: tabulate ; extra == 'testing'
Requires-Dist: tqdm ; extra == 'testing'
Requires-Dist: safetensors ; extra == 'testing'
Requires-Dist: transformers ; extra == 'testing'
Requires-Dist: sentencepiece ; extra == 'testing'
Requires-Dist: tiktoken ; extra == 'testing'
Requires-Dist: blobfile ; extra == 'testing'
Requires-Dist: librosa ; extra == 'testing'
Requires-Dist: networkx ; extra == 'testing'
Requires-Dist: hypothesis ; extra == 'testing'
Requires-Dist: nibabel ; extra == 'testing'
Requires-Dist: bottle ; extra == 'testing'
Provides-Extra: testing_tf
Requires-Dist: tensorflow ==2.15.1 ; extra == 'testing_tf'
Requires-Dist: tensorflow-addons ; extra == 'testing_tf'
Provides-Extra: triton
Requires-Dist: triton-nightly >=2.1.0.dev20231014192330 ; extra == 'triton'
